topsis_raj_102317090/__init__.py
topsis_raj_102317090/topsis.py
topsis_raj_102317090-1.0.1.dist-info/licenses/LICENSE
topsis_raj_102317090-1.0.1.dist-info/METADATA
topsis_raj_102317090-1.0.1.dist-info/WHEEL
topsis_raj_102317090-1.0.1.dist-info/entry_points.txt
topsis_raj_102317090-1.0.1.dist-info/top_level.txt
topsis_raj_102317090-1.0.1.dist-info/RECORD
