Metadata-Version: 2.4
Name: Topsis-Raj-102317090
Version: 1.0.1
Summary: A python package for implementing TOPSIS
Author: Raj
Author-email: rbrar_be23@thapar.edu
Classifier: Programming Language :: Python :: 3
Classifier: License :: OSI Approved :: MIT License
Classifier: Operating System :: OS Independent
License-File: LICENSE
Dynamic: author
Dynamic: author-email
Dynamic: classifier
Dynamic: description
Dynamic: description-content-type
Dynamic: license-file
Dynamic: summary
